havoc/__init__.py
havoc-1.0.2.dist-info/LICENSE
havoc-1.0.2.dist-info/METADATA
havoc-1.0.2.dist-info/WHEEL
havoc-1.0.2.dist-info/top_level.txt
havoc-1.0.2.dist-info/RECORD
