Metadata-Version: 2.1
Name: havoc
Version: 1.0.2
Summary: This is the ./HAVOC REST API library Package
Home-page: https://havoc.sh/
Author: Tom D'Aquino
Author-email: tom@havoc.sh
Project-URL: Bug Tracker, https://github.com/havocsh/havoc-pkg/issues
Project-URL: Documentation, https://github.com/havocsh/havoc-pkg/blob/main/README.md
Project-URL: Source Code, https://github.com/havocsh/havoc-pkg
Keywords: ./HAVOC REST API library
Classifier: License :: OSI Approved :: GNU General Public License v3 (GPLv3)
Classifier: Programming Language :: Python :: 3
Classifier: Operating System :: OS Independent
Requires-Python: >=3.7, <4
License-File: LICENSE
Requires-Dist: requests >=2.25.0
Requires-Dist: urllib3 <2
